pyem/__init__.py
pyem/__main__.py
pyem/_argparse.py
pyem/_logging.py
pyem/cmds.py
pyem/errs.py
pyem/procs.py
pyem/venvs.py
pyem/projects/__init__.py
pyem/projects/_venv.py
pyem/projects/base.py
pyem/projects/envs.py
pyem/projects/runtimes.py
pyem-2.1.0.dist-info/entry_points.txt
pyem-2.1.0.dist-info/WHEEL
pyem-2.1.0.dist-info/METADATA
pyem-2.1.0.dist-info/RECORD
