Metadata-Version: 2.1
Name: pyem
Version: 2.1.0
Summary: Project-level Python virtual environment management tool.
Home-page: https://github.com/uranusjr/pyem
License: ISC
Author: Tzu-ping Chung
Author-email: uranusjr@gmail.com
Requires-Python: >=3.7
Requires-Dist: virtualenv >=20.0.3 ; extra == "compat"
Requires-Dist: pytest ; extra == "test"
Provides-Extra: compat
Provides-Extra: test
